fargonaut/__init__.py
fargonaut/field.py
fargonaut/output.py
fargonaut/fields/__init__.py
fargonaut/fields/density.py
fargonaut/fields/energy.py
fargonaut/fields/magnetic_field.py
fargonaut/fields/velocity.py
Fargonaut-0.1.2.dist-info/LICENSE
Fargonaut-0.1.2.dist-info/METADATA
Fargonaut-0.1.2.dist-info/WHEEL
Fargonaut-0.1.2.dist-info/top_level.txt
Fargonaut-0.1.2.dist-info/RECORD
