Metadata-Version: 2.1
Name: Fargonaut
Version: 0.1.2
Summary: A FARGO3D output post-processing and visualisation toolkit
Author-email: Dan Cummins <daniel.cummins17@imperial.ac.uk>
License: BSD 3-Clause License
Project-URL: Homepage, https://github.com/dc2917/Fargonaut
Project-URL: Documentation, https://dc2917.github.io/Fargonaut/index.html
Keywords: astronomy,astrophysics,fargo3d,visualisation
Classifier: Programming Language :: Python :: 3
Classifier: License :: OSI Approved :: BSD License
Requires-Python: >=3.12
License-File: LICENSE
Requires-Dist: matplotlib
Requires-Dist: numpy
Provides-Extra: dev
Requires-Dist: pip-tools ; extra == 'dev'
Requires-Dist: pre-commit ; extra == 'dev'
Requires-Dist: ruff ; extra == 'dev'
Requires-Dist: sphinx ; extra == 'dev'
Requires-Dist: sphinx-rtd-theme ; extra == 'dev'
